{
  "summary": "2 Behind the cross is a sandstone wall divided into five sections by six piers , each section containing a marble plaque",
  "key_points": [
    "2 Behind the cross is a sandstone wall divided into five sections by six piers , each section containing a marble plaque"
  ],
  "keywords": [],
  "source": "https://en.wikipedia.org/wiki/Special:Random",
  "title": "Insight from https://en.wikipedia.org/wiki/Special:Random",
  "timestamp": 1772344624.0170972,
  "language": "en",
  "word_count": 22,
  "id": "a8108895870efffd"
}