{
  "id": "1823a4490b33032e",
  "content": "Pascal Caucheteux - Wikipedia function ; document.documentElement.className className; ;RLCONF ,\"wgConfirmEditCaptchaNeededForGenericEdit\":\"hcaptcha\",\" \":false,\"wgConfirmEditHCaptchaSiteKey\":\"5d0c670e-a5f4-4258-ad16-1f42792c9c62\",\"wgMediaViewerOnClick\":true,\"wgMediaViewerEnabledByDefault\":true,\"wgPopupsFlags\":0,\"wgVisualEditor\": ,\"wgMFDisplayWikibaseDescriptions\": ,\"wgWMESchemaEditAttemptStepOversample\":false,\"wgWMEPageLength\":4000,\"wgEditSubmitButtonLabelPublish\":true,\"wgVisualEditorPageIsDisambiguation\":false,\"wgULSPosition\":\"interlanguage\",\"wgULSisCompactLinksEnabled\":false,\"wgVector2022LanguageInHeader\":true,\"wgULSisLanguageSelectorEmpty\":false,\"wgWikibaseItemId\":\"Q3367324\",\"wgCheckUserClientHintsHeadersJsApi\": \"brands\",\"architecture\",\"bitness\",\"fullVersionList\",\"mobile\",\"model\",\"platform\",\"platformVersion\" ,\"GEHomepageSuggestedEditsEnableTopics\":true,\"wgGESuggestedEditsTaskTypes\": ,\"wgGETopicsMatchModeEnabled\":false,\"wgGELevelingUpEnabledForUser\":false,\"wgGEUseTestKitchenExtension\":true,\"wgMetricsPlatformUserExperiments\": ,\"wgTestKitchenUserExperiments\": ; RLSTATE ;RLPAGEMODULES \"ext.parsermigration.survey\",\"ext.cite.ux-enhancements\",\"site\",\"mediawiki.page.ready\",\"jquery.makeCollapsible\",\"skins.vector.js\",\"ext.centralNotice.geoIP\",\"ext.centralNotice.startUp\",\"ext.gadget.ReferenceTooltips\",\"ext.gadget.switcher\",\"ext.urlShortener.toolbar\",\"ext.centralauth.centralautologin\",\"mmv.bootstrap\",\"ext.popups\",\"ext.visualEditor.desktopArticleTarget.init\",\"ext.echo.centralauth\",\"ext.eventLogging\",\"ext.wikimediaEvents\",\"ext.navigationTiming\",\"ext.uls.interface\",\"ext.cx.eventlogging.campaigns\",\"ext.cx.uls.quick.actions\",\"wikibase.client.vector-2022\",\"wikibase.databox.fromWikidata\",\"ext.checkUser.clientHints\",\"ext.quicksurveys.init\",\"ext.growthExperiments.SuggestedEditSession\",\"ext.xLab\",\"ext.testKitchen\",\"ext.wp25EasterEggs\" ; RLQ window.RLQ .push function ; ; ; ; Jump to content Main menu Main menu move to sidebar hide Navigation Main page Contents Current events Random article About Wikipedia Contact us Contribute Help Learn to edit Community portal Recent changes Upload file Special pages Search Search Appearance Donate Create account Log in Personal tools Donate Create account Log in Contents move to sidebar hide Top 1 Selected filmography 2 References 3 External links Toggle the table of contents Pascal Caucheteux 5 languages العربية مصرى Deutsch Français Italiano Edit links Article Talk English Read Edit View history Tools Tools move to sidebar hide Actions Read Edit View history General What links here Related changes Upload file Permanent link Page information Cite this page Get shortened URL Download QR code Print export Download as PDF Printable version In other projects Wikimedia Commons Wikidata item Appearance move to sidebar hide From Wikipedia, the free encyclopedia French film producer .mw-parser-output .infobox-subbox .mw-parser-output .infobox-3cols-child .mw-parser-output .infobox .navbar screen screen and prefers-color-scheme:dark min-width:640px body.skin--responsive .mw-parser-output .infobox-table caption body.skin--responsive .mw-parser-output .infobox-table tbody body.skin--responsive .mw-parser-output .infobox-table th,body.skin--responsive .mw-parser-output .infobox-table td Pascal Caucheteux Caucheteux in 2008 Born 1961-03-27 27 March 1961 age 64 Vincennes , France Occupation Film producer Years active 1991 present Pascal Caucheteux born 27 March 1961 1 is a French film producer . 2 In 1990, together with Grégoire Sorlat, he founded the company Why Not Productions to finance French auteur cinema, in which he is considered a pivotal figure. 3 4 He won three British Academy Film Awards and was nominated for five more in the categories Best Film , Outstanding British Film and Best Film Not in the English Language . At the 97th Academy Awards , he was nominated for an Academy Award in the category Best Picture for the film Emilia Pérez . 5 His nomination was shared with Jacques Audiard . 6 7 8 Selected filmography edit The Beat That My Heart Skipped 2005 A Prophet 2009 Of Gods and Men 2010 Rust and Bone 2012 Dheepan 2015 You Were Never Really Here 2017 Emilia Pérez 2024 References edit .mw-parser-output .reflist-columns-2 .mw-parser-output .reflist-columns-3 body.skin-vector-2022 .mw-parser-output .reflist-columns-2 body.skin-vector-2022 .mw-parser-output .reflist-columns-3 .mw-parser-output .references data-mw-group upper-alpha .mw-parser-output .references data-mw-group upper-roman .mw-parser-output .references data-mw-group lower-alpha .mw-parser-output .references data-mw-group lower-greek .mw-parser-output .references data-mw-group lower-roman .mw-parser-output div.reflist-liststyle-upper-alpha .references .mw-parser-output div.reflist-liststyle-upper-roman .references .mw-parser-output div.reflist-liststyle-lower-alpha .references .mw-parser-output div.reflist-liststyle-lower-greek .references .mw-parser-output div.reflist-liststyle-lower-roman .references .mw-parser-output cite.citation .mw-parser-output .citation q .mw-parser-output .citation:target .mw-parser-output .id-lock-free.id-lock-free a .mw-parser-output .id-lock-limited.id-lock-limited a,.mw-parser-output .id-lock-registration.id-lock-registration a .mw-parser-output .id-lock-subscription.id-lock-subscription a .mw-parser-output .cs1-ws-icon a body:not .skin-timeless :not .skin-minerva .mw-parser-output .id-lock-free a,body:not .skin-timeless :not .skin-minerva .mw-parser-output .id-lock-limited a,body:not .skin-timeless :not .skin-minerva .mw-parser-output .id-lock-registration a,body:not .skin-timeless :not .skin-minerva .mw-parser-output .id-lock-subscription a,body:not .skin-timeless :not .skin-minerva .mw-parser-output .cs1-ws-icon a .mw-parser-output .cs1-code .mw-parser-output .cs1-hidden-error .mw-parser-output .cs1-visible-error .mw-parser-output .cs1-maint .mw-parser-output .cs1-kern-left .mw-parser-output .cs1-kern-right .mw-parser-output .citation .mw-selflink screen html.skin-theme-clientpref-night .mw-parser-output .cs1-maint screen and prefers-color-scheme:dark \"Pascal Caucheteux\" . Rotten Tomatoes . Retrieved 2 March 2025 . Keslassy, Elsa 24 February 2009 . \"French academy fetes producing pair\" . Variety . Retrieved 2 March 2025 . \"Les 30 qui font le cinéma français en 2009: No 27: Pascal Caucheteux\" . L'Express . 13 May 2009. \"Why Not Productions, les meneurs de jeu du cinéma français\" . Télérama . No. 3207. 2 July 2011. \"The 97th Academy Awards 2025 Nominees and Winners\" . Academy of Motion Picture Arts and Sciences . Retrieved 2 March 2025 . Fleming, Mike Jr.; Hipes, Patrick 23 January 2025 . \"Oscar Nominations: 'Emilia Pérez' Leads With 13; 'The Brutalist' And 'Wicked' Score 10 Apiece In Wide-Open Race\" . Deadline Hollywood . Retrieved 2 March 2025 . Lewis, Hilary; Nordyke, Kimberly 23 January 2025 . \"Oscars: Full List of Nominees\" . The Hollywood Reporter . Retrieved 2 March 2025 . Lang, Brent; Moreay, Jordan 23 January 2025 . \"Oscar Nominations 2025: 'Emilia Pérez' Leads With 13 Nods, 'Wicked' and 'The Brutalist' Follow With 10\" . Variety . Retrieved 2 March 2025 . External links edit Pascal Caucheteux at IMDb .mw-parser-output .hlist dl,.mw-parser-output .hlist ol,.mw-parser-output .hlist ul .mw-parser-output .hlist dd,.mw-parser-output .hlist dt,.mw-parser-output .hlist li .mw-parser-output .hlist.inline,.mw-parser-output .hlist.inline dl,.mw-parser-output .hlist.inline ol,.mw-parser-output .hlist.inline ul,.mw-parser-output .hlist dl dl,.mw-parser-output .hlist dl ol,.mw-parser-output .hlist dl ul,.mw-parser-output .hlist ol dl,.mw-parser-output .hlist ol ol,.mw-parser-output .hlist ol ul,.mw-parser-output .hlist ul dl,.mw-parser-output .hlist ul ol,.mw-parser-output .hlist ul ul .mw-parser-output .hlist .mw-empty-li .mw-parser-output .hlist dt::after .mw-parser-output .hlist dd::after,.mw-parser-output .hlist li::after .mw-parser-output .hlist dd:last-child::after,.mw-parser-output .hlist dt:last-child::after,.mw-parser-output .hlist li:last-child::after .mw-parser-output .hlist dd dd:first-child::before,.mw-parser-output .hlist dd dt:first-child::before,.mw-parser-output .hlist dd li:first-child::before,.mw-parser-output .hlist dt dd:first-child::before,.mw-parser-output .hlist dt dt:first-child::before,.mw-parser-output .hlist dt li:first-child::before,.mw-parser-output .hlist li dd:first-child::before,.mw-parser-output .hlist li dt:first-child::before,.mw-parser-output .hlist li li:first-child::before .mw-parser-output .hlist dd dd:last-child::after,.mw-parser-output .hlist dd dt:last-child::after,.mw-parser-output .hlist dd li:last-child::after,.mw-parser-output .hlist dt dd:last-child::after,.mw-parser-output .hlist dt dt:last-child::after,.mw-parser-output .hlist dt li:last-child::after,.mw-parser-output .hlist li dd:last-child::after,.mw-parser-output .hlist li dt:last-child::after,.mw-parser-output .hlist li li:last-child::after .mw-parser-output .hlist ol .mw-parser-output .hlist ol li .mw-parser-output .hlist ol li::before .mw-parser-output .hlist dd ol li:first-child::before,.mw-parser-output .hlist dt ol li:first-child::before,.mw-parser-output .hlist li ol li:first-child::before .mw-parser-output .navbox .mw-parser-output .navbox .navbox .mw-parser-output .navbox .navbox,.mw-parser-output .navbox .navbox-styles .navbox .mw-parser-output .navbox-inner,.mw-parser-output .navbox-subgroup .mw-parser-output .navbox-group,.mw-parser-output .navbox-title,.mw-parser-output .navbox-abovebelow .mw-parser-output .navbox-group .mw-parser-output .navbox,.mw-parser-output .navbox-subgroup .mw-parser-output .navbox-list .mw-parser-output .navbox-list-with-group .mw-parser-output tr tr .navbox-abovebelow,.mw-parser-output tr tr .navbox-group,.mw-parser-output tr tr .navbox-image,.mw-parser-output tr tr .navbox-list .mw-parser-output .navbox-title .mw-parser-output .navbox-abovebelow,.mw-parser-output .navbox-group,.mw-parser-output .navbox-subgroup .navbox-title .mw-parser-output .navbox-subgroup .navbox-group,.mw-parser-output .navbox-subgroup .navbox-abovebelow .mw-parser-output .navbox-even .mw-parser-output .navbox-odd .mw-parser-output .navbox .hlist td dl,.mw-parser-output .navbox .hlist td ol,.mw-parser-output .navbox .hlist td ul,.mw-parser-output .navbox td.hlist dl,.mw-parser-output .navbox td.hlist ol,.mw-parser-output .navbox td.hlist ul .mw-parser-output .navbox .navbar .mw-parser-output .navbox-title .navbar body.skin--responsive .mw-parser-output .navbox-image img print Authority control databases International ISNI VIAF GND WorldCat National United States Netherlands Poland Catalonia Academics CiNii People Deutsche Biographie Other Yale LUX .mw-parser-output .asbox .mw-parser-output .asbox table .mw-parser-output .asbox p .mw-parser-output .asbox p p .mw-parser-output .asbox-body .mw-parser-output .asbox-note .mw-parser-output .asbox .navbar .mw-parser-output :not p :not .asbox style .asbox,.mw-parser-output :not p :not .asbox link .asbox This biographical article related to film in France is a stub . You can help Wikipedia by adding missing information . .mw-parser-output .navbar .mw-parser-output .navbar-collapse .mw-parser-output .navbar-boxtext .mw-parser-output .navbar ul .mw-parser-output .navbar-brackets::before .mw-parser-output .navbar-brackets::after .mw-parser-output .navbar li .mw-parser-output .navbar a span,.mw-parser-output .navbar a abbr .mw-parser-output .navbar-mini abbr .mw-parser-output .navbar-ct-full .mw-parser-output .navbar-ct-mini html.skin-theme-clientpref-night .mw-parser-output .navbar li a abbr prefers-color-scheme:dark print v t e Retrieved from \" \" Categories : 1961 births Living people People from Vincennes French film producers Best Film César Award winners Best Foreign Film César Award winners Producers who won the Best Foreign Language Film BAFTA Award French film biography stubs Hidden categories: Articles with short description Short description matches Wikidata Use dmy dates from March 2025 Articles with hCards All stub articles This page was last edited on 11 October 2025, at 05:03 UTC . Text is available under the Creative Commons Attribution-ShareAlike 4.0 License ; additional terms may apply. By using this site, you agree to the Terms of Use and Privacy Policy . Wikipedia is a registered trademark of the Wikimedia Foundation, Inc. , a non-profit organization. Privacy policy About Wikipedia Disclaimers Contact Wikipedia Legal safety contacts Code of Conduct Developers Statistics Cookie statement Mobile view Search Search Toggle the table of contents Pascal Caucheteux 5 languages Add topic RLQ window.RLQ .push function ,\"revisionsize\": ,\"postexpandincludesize\": ,\"templateargumentsize\": ,\"expansiondepth\": ,\"expensivefunctioncount\": ,\"unstrip-depth\": ,\"unstrip-size\": ,\"entityaccesscount\": ,\"timingprofile\": \"100.00 473.234 1 -total\",\" 28.76 136.116 1 Template:Infobox_person\",\" 26.91 127.334 1 Template:Reflist\",\" 20.65 97.736 6 Template:Cite_web\",\" 14.51 68.688 1 Template:Authority_control\",\" 13.89 65.752 1 Template:Short_description\",\" 8.68 41.081 4 Template:Br_separated_entries\",\" 8.22 38.891 2 Template:Pagetype\",\" 8.19 38.777 1 Template:France-film-bio-stub\",\" 7.82 36.992 1 Template:Asbox\" ,\"scribunto\": ,\"limitreport-memusage\": ,\"cachereport\": ; ; ,\"publisher\": ,\"datePublished\":\"2025-03-02T23:13:01Z\",\"dateModified\":\"2025-10-11T05:03:01Z\",\"image\":\"https: upload.wikimedia.org wikipedia commons a a5 Pascal_Caucheteux.jpg\",\"headline\":\"French film producer\"",
  "summary": "Pascal Caucheteux - Wikipedia function ; document.documentElement.className className; ;RLCONF ,\"wgConfirmEditCaptchaNeededForGenericEdit\":\"hcaptcha\",\" \":false,\"wgConfirmEditHCaptchaSiteKey\":\"5d0c670e-a5f4-4258-ad16-1f42792c9c62\",\"wgMediaViewerOnClick\":true,\"wgMediaViewerEnabledByDefault\":true,\"wgPopupsFlags\":0,\"wgVisualEditor\": ,\"wgMFDisplayWikibaseDescriptions\": ,\"wgWMESchemaEditAttemptStepOversample\":false,\"wgWMEPageLength\":4000,\"wgEditSubmitButtonLabelPublish\":true,\"wgVisualEditorPageIsDisambiguation\":false,\"wgULSPosition\":\"interlanguage\",\"wgULSisCompactLinksEnabled\":false,\"wgVector2022LanguageInHeader\":true,\"wgULSisLanguageSelectorEmpty\":false,\"wgWikibaseItemId\":\"Q3367324\",\"wgCheckUserClientHintsHeadersJsApi\": \"brands\",\"architecture\",\"bitness\",\"fullVersionList\",\"mobile\",\"model\",\"platform\",\"platformVersion\" ,\"GEHomepageSuggestedEditsEnableTopics\":true,\"wgGESuggestedEditsTaskTypes\": ,\"wgGETopicsMatchModeEnabled\":false,\"wgGELevelingUpEnabledForUser\":false,\"wgGEUseTestKitchenExtension\":true,\"wgMetricsPlatformUserExperiments\": ,\"wgTestKitchenUserExperiments\": ; RLSTATE ;RLPAGEMODULES \"ext.parsermigration.survey\",\"ext.cite.ux-enhancements\",\"site\",\"mediawiki.page.ready\",\"jquery.makeCollapsible\",\"skins.vector.js\",\"ext.centralNotice.geoIP\",\"ext.centralNotice.startUp\",\"ext.gadget.ReferenceTooltips\",\"ext.gadget.switcher\",\"ext.urlShortener.toolbar\",\"ext.centralauth.centralautologin\",\"mmv.bootstrap\",\"ext.popups\",\"ext.visualEditor.desktopArticleTarget.init\",\"ext.echo.centralauth\",\"ext.eventLogging\",\"ext.wikimediaEvents\",\"ext.navigationTiming\",\"ext.uls.interface\",\"ext.cx.eventlogging.campaigns\",\"ext.cx.uls.quick.actions\",\"wikibase.client.vector-2022\",\"wikibase.databox.fromWikidata\",\"ext.checkUser.clientHints\",\"ext.quicksurveys.init\",\"ext.growthExperiments.SuggestedEditSession\",\"ext.xLab\",\"ext.testKitchen\",\"ext.wp25EasterEggs\" ; RLQ window.RLQ .push function ; ; ; ; Jump to content Main menu Main menu move to sidebar hide Navigation Main page Contents Current events Random article About Wikipedia Contact us Contribute Help Learn to edit Community portal Recent changes Upload file Special pages Search Search Appearance Donate Create account Log in Personal tools Donate Create account Log in Contents move to sidebar hide Top 1 Selected filmography 2 References 3 External links Toggle the table of contents Pascal Caucheteux 5 languages العربية مصرى Deutsch Français Italiano Edit links Article Talk English Read Edit View history Tools Tools move to sidebar hide Actions Read Edit View history General What links here Related changes Upload file Permanent link Page information Cite this page Get shortened URL Download QR code Print export Download as PDF Printable version In other projects Wikimedia Commons Wikidata item Appearance move to sidebar hide From Wikipedia, the free encyclopedia French film producer .mw-parser-output .infobox-subbox .mw-parser-output .infobox-3cols-child .mw-parser-output .infobox .navbar screen screen and prefers-color-scheme:dark min-width:640px body.skin--responsive .mw-parser-output .infobox-table caption body.skin--responsive .mw-parser-output .infobox-table tbody body.skin--responsive .mw-parser-output .infobox-table th,body.skin--responsive .mw-parser-output .infobox-table td Pascal Caucheteux Caucheteux in 2008 Born 1961-03-27 27 March 1961 age 64 Vincennes , France Occupation Film producer Years active 1991 present Pascal Caucheteux born 27 March 1961 1 is a French film producer . 6 7 8 Selected filmography edit The Beat That My Heart Skipped 2005 A Prophet 2009 Of Gods and Men 2010 Rust and Bone 2012 Dheepan 2015 You Were Never Really Here 2017 Emilia Pérez 2024 References edit .mw-parser-output .reflist-columns-2 .mw-parser-output .reflist-columns-3 body.skin-vector-2022 .mw-parser-output .reflist-columns-2 body.skin-vector-2022 .mw-parser-output .reflist-columns-3 .mw-parser-output .references data-mw-group upper-alpha .mw-parser-output .references data-mw-group upper-roman .mw-parser-output .references data-mw-group lower-alpha .mw-parser-output .references data-mw-group lower-greek .mw-parser-output .references data-mw-group lower-roman .mw-parser-output div.reflist-liststyle-upper-alpha .references .mw-parser-output div.reflist-liststyle-upper-roman .references .mw-parser-output div.reflist-liststyle-lower-alpha .references .mw-parser-output div.reflist-liststyle-lower-greek .references .mw-parser-output div.reflist-liststyle-lower-roman .references .mw-parser-output cite.citation .mw-parser-output .citation q .mw-parser-output .citation:target .mw-parser-output .id-lock-free.id-lock-free a .mw-parser-output .id-lock-limited.id-lock-limited a,.mw-parser-output .id-lock-registration.id-lock-registration a .mw-parser-output .id-lock-subscription.id-lock-subscription a .mw-parser-output .cs1-ws-icon a body:not .skin-timeless :not .skin-minerva .mw-parser-output .id-lock-free a,body:not .skin-timeless :not .skin-minerva .mw-parser-output .id-lock-limited a,body:not .skin-timeless :not .skin-minerva .mw-parser-output .id-lock-registration a,body:not .skin-timeless :not .skin-minerva .mw-parser-output .id-lock-subscription a,body:not .skin-timeless :not .skin-minerva .mw-parser-output .cs1-ws-icon a .mw-parser-output .cs1-code .mw-parser-output .cs1-hidden-error .mw-parser-output .cs1-visible-error .mw-parser-output .cs1-maint .mw-parser-output .cs1-kern-left .mw-parser-output .cs1-kern-right .mw-parser-output .citation .mw-selflink screen html.skin-theme-clientpref-night .mw-parser-output .cs1-maint screen and prefers-color-scheme:dark \"Pascal Caucheteux\" . Retrieved 2 March 2025 . .mw-parser-output .navbar .mw-parser-output .navbar-collapse .mw-parser-output .navbar-boxtext .mw-parser-output .navbar ul .mw-parser-output .navbar-brackets::before .mw-parser-output .navbar-brackets::after .mw-parser-output .navbar li .mw-parser-output .navbar a span,.mw-parser-output .navbar a abbr .mw-parser-output .navbar-mini abbr .mw-parser-output .navbar-ct-full .mw-parser-output .navbar-ct-mini html.skin-theme-clientpref-night .mw-parser-output .navbar li a abbr prefers-color-scheme:dark print v t e Retrieved from \" \" Categories : 1961 births Living people People from Vincennes French film producers Best Film César Award winners Best Foreign Film César Award winners Producers who won the Best Foreign Language Film BAFTA Award French film biography stubs Hidden categories: Articles with short description Short description matches Wikidata Use dmy dates from March 2025 Articles with hCards All stub articles This page was last edited on 11 October 2025, at 05:03 UTC . Privacy policy About Wikipedia Disclaimers Contact Wikipedia Legal safety contacts Code of Conduct Developers Statistics Cookie statement Mobile view Search Search Toggle the table of contents Pascal Caucheteux 5 languages Add topic RLQ window.RLQ .push function ,\"revisionsize\": ,\"postexpandincludesize\": ,\"templateargumentsize\": ,\"expansiondepth\": ,\"expensivefunctioncount\": ,\"unstrip-depth\": ,\"unstrip-size\": ,\"entityaccesscount\": ,\"timingprofile\": \"100.00 473.234 1 -total\",\" 28.76 136.116 1 Template:Infobox_person\",\" 26.91 127.334 1 Template:Reflist\",\" 20.65 97.736 6 Template:Cite_web\",\" 14.51 68.688 1 Template:Authority_control\",\" 13.89 65.752 1 Template:Short_description\",\" 8.68 41.081 4 Template:Br_separated_entries\",\" 8.22 38.891 2 Template:Pagetype\",\" 8.19 38.777 1 Template:France-film-bio-stub\",\" 7.82 36.992 1 Template:Asbox\" ,\"scribunto\": ,\"limitreport-memusage\": ,\"cachereport\": ; ; ,\"publisher\": ,\"datePublished\":\"2025-03-02T23:13:01Z\",\"dateModified\":\"2025-10-11T05:03:01Z\",\"image\":\"https: upload.wikimedia.org wikipedia commons a a5 Pascal_Caucheteux.jpg\",\"headline\":\"French film producer\"",
  "key_points": [
    "Pascal Caucheteux - Wikipedia function ; document.documentElement.className className; ;RLCONF ,\"wgConfirmEditCaptchaNeededForGenericEdit\":\"hcaptcha\",\" \":false,\"wgConfirmEditHCaptchaSiteKey\":\"5d0c670e-a5f4-4258-ad16-1f42792c9c62\",\"wgMediaViewerOnClick\":true,\"wgMediaViewerEnabledByDefault\":true,\"wgPopupsFlags\":0,\"wgVisualEditor\": ,\"wgMFDisplayWikibaseDescriptions\": ,\"wgWMESchemaEditAttemptStepOversample\":false,\"wgWMEPageLength\":4000,\"wgEditSubmitButtonLabelPublish\":true,\"wgVisualEditorPageIsDisambiguation\":false,\"wgULSPosition\":\"interlanguage\",\"wgULSisCompactLinksEnabled\":false,\"wgVector2022LanguageInHeader\":true,\"wgULSisLanguageSelectorEmpty\":false,\"wgWikibaseItemId\":\"Q3367324\",\"wgCheckUserClientHintsHeadersJsApi\": \"brands\",\"architecture\",\"bitness\",\"fullVersionList\",\"mobile\",\"model\",\"platform\",\"platformVersion\" ,\"GEHomepageSuggestedEditsEnableTopics\":true,\"wgGESuggestedEditsTaskTypes\": ,\"wgGETopicsMatchModeEnabled\":false,\"wgGELevelingUpEnabledForUser\":false,\"wgGEUseTestKitchenExtension\":true,\"wgMetricsPlatformUserExperiments\": ,\"wgTestKitchenUserExperiments\": ; RLSTATE ;RLPAGEMODULES \"ext.parsermigration.survey\",\"ext.cite.ux-enhancements\",\"site\",\"mediawiki.page.ready\",\"jquery.makeCollapsible\",\"skins.vector.js\",\"ext.centralNotice.geoIP\",\"ext.centralNotice.startUp\",\"ext.gadget.ReferenceTooltips\",\"ext.gadget.switcher\",\"ext.urlShortener.toolbar\",\"ext.centralauth.centralautologin\",\"mmv.bootstrap\",\"ext.popups\",\"ext.visualEditor.desktopArticleTarget.init\",\"ext.echo.centralauth\",\"ext.eventLogging\",\"ext.wikimediaEvents\",\"ext.navigationTiming\",\"ext.uls.interface\",\"ext.cx.eventlogging.campaigns\",\"ext.cx.uls.quick.actions\",\"wikibase.client.vector-2022\",\"wikibase.databox.fromWikidata\",\"ext.checkUser.clientHints\",\"ext.quicksurveys.init\",\"ext.growthExperiments.SuggestedEditSession\",\"ext.xLab\",\"ext.testKitchen\",\"ext.wp25EasterEggs\" ; RLQ window.RLQ .push function ; ; ; ; Jump to content Main menu Main menu move to sidebar hide Navigation Main page Contents Current events Random article About Wikipedia Contact us Contribute Help Learn to edit Community portal Recent changes Upload file Special pages Search Search Appearance Donate Create account Log in Personal tools Donate Create account Log in Contents move to sidebar hide Top 1 Selected filmography 2 References 3 External links Toggle the table of contents Pascal Caucheteux 5 languages العربية مصرى Deutsch Français Italiano Edit links Article Talk English Read Edit View history Tools Tools move to sidebar hide Actions Read Edit View history General What links here Related changes Upload file Permanent link Page information Cite this page Get shortened URL Download QR code Print export Download as PDF Printable version In other projects Wikimedia Commons Wikidata item Appearance move to sidebar hide From Wikipedia, the free encyclopedia French film producer .mw-parser-output .infobox-subbox .mw-parser-output .infobox-3cols-child .mw-parser-output .infobox .navbar screen screen and prefers-color-scheme:dark min-width:640px body.skin--responsive .mw-parser-output .infobox-table caption body.skin--responsive .mw-parser-output .infobox-table tbody body.skin--responsive .mw-parser-output .infobox-table th,body.skin--responsive .mw-parser-output .infobox-table td Pascal Caucheteux Caucheteux in 2008 Born 1961-03-27 27 March 1961 age 64 Vincennes , France Occupation Film producer Years active 1991 present Pascal Caucheteux born 27 March 1961 1 is a French film producer .",
    "6 7 8 Selected filmography edit The Beat That My Heart Skipped 2005 A Prophet 2009 Of Gods and Men 2010 Rust and Bone 2012 Dheepan 2015 You Were Never Really Here 2017 Emilia Pérez 2024 References edit .mw-parser-output .reflist-columns-2 .mw-parser-output .reflist-columns-3 body.skin-vector-2022 .mw-parser-output .reflist-columns-2 body.skin-vector-2022 .mw-parser-output .reflist-columns-3 .mw-parser-output .references data-mw-group upper-alpha .mw-parser-output .references data-mw-group upper-roman .mw-parser-output .references data-mw-group lower-alpha .mw-parser-output .references data-mw-group lower-greek .mw-parser-output .references data-mw-group lower-roman .mw-parser-output div.reflist-liststyle-upper-alpha .references .mw-parser-output div.reflist-liststyle-upper-roman .references .mw-parser-output div.reflist-liststyle-lower-alpha .references .mw-parser-output div.reflist-liststyle-lower-greek .references .mw-parser-output div.reflist-liststyle-lower-roman .references .mw-parser-output cite.citation .mw-parser-output .citation q .mw-parser-output .citation:target .mw-parser-output .id-lock-free.id-lock-free a .mw-parser-output .id-lock-limited.id-lock-limited a,.mw-parser-output .id-lock-registration.id-lock-registration a .mw-parser-output .id-lock-subscription.id-lock-subscription a .mw-parser-output .cs1-ws-icon a body:not .skin-timeless :not .skin-minerva .mw-parser-output .id-lock-free a,body:not .skin-timeless :not .skin-minerva .mw-parser-output .id-lock-limited a,body:not .skin-timeless :not .skin-minerva .mw-parser-output .id-lock-registration a,body:not .skin-timeless :not .skin-minerva .mw-parser-output .id-lock-subscription a,body:not .skin-timeless :not .skin-minerva .mw-parser-output .cs1-ws-icon a .mw-parser-output .cs1-code .mw-parser-output .cs1-hidden-error .mw-parser-output .cs1-visible-error .mw-parser-output .cs1-maint .mw-parser-output .cs1-kern-left .mw-parser-output .cs1-kern-right .mw-parser-output .citation .mw-selflink screen html.skin-theme-clientpref-night .mw-parser-output .cs1-maint screen and prefers-color-scheme:dark \"Pascal Caucheteux\" .",
    "Retrieved 2 March 2025 .",
    ".mw-parser-output .navbar .mw-parser-output .navbar-collapse .mw-parser-output .navbar-boxtext .mw-parser-output .navbar ul .mw-parser-output .navbar-brackets::before .mw-parser-output .navbar-brackets::after .mw-parser-output .navbar li .mw-parser-output .navbar a span,.mw-parser-output .navbar a abbr .mw-parser-output .navbar-mini abbr .mw-parser-output .navbar-ct-full .mw-parser-output .navbar-ct-mini html.skin-theme-clientpref-night .mw-parser-output .navbar li a abbr prefers-color-scheme:dark print v t e Retrieved from \" \" Categories : 1961 births Living people People from Vincennes French film producers Best Film César Award winners Best Foreign Film César Award winners Producers who won the Best Foreign Language Film BAFTA Award French film biography stubs Hidden categories: Articles with short description Short description matches Wikidata Use dmy dates from March 2025 Articles with hCards All stub articles This page was last edited on 11 October 2025, at 05:03 UTC .",
    "Privacy policy About Wikipedia Disclaimers Contact Wikipedia Legal safety contacts Code of Conduct Developers Statistics Cookie statement Mobile view Search Search Toggle the table of contents Pascal Caucheteux 5 languages Add topic RLQ window.RLQ .push function ,\"revisionsize\": ,\"postexpandincludesize\": ,\"templateargumentsize\": ,\"expansiondepth\": ,\"expensivefunctioncount\": ,\"unstrip-depth\": ,\"unstrip-size\": ,\"entityaccesscount\": ,\"timingprofile\": \"100.00 473.234 1 -total\",\" 28.76 136.116 1 Template:Infobox_person\",\" 26.91 127.334 1 Template:Reflist\",\" 20.65 97.736 6 Template:Cite_web\",\" 14.51 68.688 1 Template:Authority_control\",\" 13.89 65.752 1 Template:Short_description\",\" 8.68 41.081 4 Template:Br_separated_entries\",\" 8.22 38.891 2 Template:Pagetype\",\" 8.19 38.777 1 Template:France-film-bio-stub\",\" 7.82 36.992 1 Template:Asbox\" ,\"scribunto\": ,\"limitreport-memusage\": ,\"cachereport\": ; ; ,\"publisher\": ,\"datePublished\":\"2025-03-02T23:13:01Z\",\"dateModified\":\"2025-10-11T05:03:01Z\",\"image\":\"https: upload.wikimedia.org wikipedia commons a a5 Pascal_Caucheteux.jpg\",\"headline\":\"French film producer\""
  ],
  "keywords": [
    "parser",
    "output",
    "hlist",
    "navbox",
    "child",
    "ext",
    "skin",
    "navbar",
    "film",
    "2025",
    "body",
    "last",
    "references",
    "lock",
    "first"
  ],
  "source": "https://en.wikipedia.org/wiki/Special:Random",
  "length": 13470,
  "quality": 0.45200035958609486,
  "type": "article",
  "hash": "1823a4490b33032eacda7c841c5d997c2b801afee7021be3cf3eff94732a2f02",
  "language": "en",
  "original_language": "en",
  "timestamp": "2026-03-04T02:34:03.636652",
  "metadata": {}
}