{
  "id": "f089be0e7122dbf2",
  "content": "Evolved code for evolve_2ba43c: def auto_evolve_2ba43c_1772341944 arg1, arg2 : result None result arg1 arg2 result...",
  "summary": "Evolved code for evolve_2ba43c: def auto_evolve_2ba43c_1772341944 arg1, arg2 : result None result arg1 arg2 result...",
  "key_points": [
    "Evolved code for evolve_2ba43c: def auto_evolve_2ba43c_1772341944 arg1, arg2 : result None result arg1 arg2 result..."
  ],
  "keywords": [
    "result",
    "arg1",
    "arg2",
    "evolved",
    "code",
    "evolve_2ba43c",
    "def",
    "auto_evolve_2ba43c_1772341944",
    "none"
  ],
  "source": "evolution",
  "length": 117,
  "quality": 0.6829059829059829,
  "type": "unknown",
  "hash": "f089be0e7122dbf22b7a2d02fab818463cba78e76c4e72bc3bb44926f20af80d",
  "language": "en",
  "original_language": "en",
  "timestamp": "2026-03-01T13:12:30.360397",
  "metadata": {}
}