{
  "id": "43f57c3a7208a0ae",
  "content": "GitHub public-apis public-apis: A collective list of free APIs 401170",
  "summary": "GitHub public-apis public-apis: A collective list of free APIs 401170",
  "key_points": [
    "GitHub public-apis public-apis: A collective list of free APIs 401170"
  ],
  "keywords": [
    "apis",
    "public",
    "github",
    "collective",
    "list",
    "free",
    "401170"
  ],
  "source": "github:trending",
  "length": 69,
  "quality": 0.7956521739130435,
  "type": "unknown",
  "hash": "43f57c3a7208a0aec3b0845162dd018d1b189194dfeb9ec0e7e01407bdbba0ab",
  "language": "en",
  "original_language": "en",
  "timestamp": "2026-02-28T22:40:46.599243",
  "metadata": {}
}