{
  "id": "f69aef6bbacb989e",
  "content": "GitHub vinta awesome-python: An opinionated list of awesome Python frameworks, libraries, software and resources. 284632",
  "summary": "GitHub vinta awesome-python: An opinionated list of awesome Python frameworks, libraries, software and resources. 284632",
  "key_points": [
    "GitHub vinta awesome-python: An opinionated list of awesome Python frameworks, libraries, software and resources.",
    "284632"
  ],
  "keywords": [
    "awesome",
    "python",
    "github",
    "vinta",
    "opinionated",
    "list",
    "frameworks",
    "libraries",
    "software",
    "resources",
    "284632"
  ],
  "source": "github:trending",
  "length": 120,
  "quality": 0.9166666666666666,
  "type": "unknown",
  "hash": "f69aef6bbacb989e05bd034a9f590bd416089858a59b103d1f9d3302082b57f0",
  "language": "en",
  "original_language": "en",
  "timestamp": "2026-02-26T12:58:20.675873",
  "metadata": {}
}