{
  "id": "f66168437f38fd54",
  "content": "ai 409 points by tin7in 15 hours ago hide 171 comments 7",
  "summary": "ai 409 points by tin7in 15 hours ago hide 171 comments 7",
  "key_points": [
    "ai 409 points by tin7in 15 hours ago hide 171 comments 7"
  ],
  "keywords": [
    "409",
    "points",
    "tin7in",
    "hours",
    "ago",
    "hide",
    "171",
    "comments"
  ],
  "source": "https://news.ycombinator.com",
  "length": 56,
  "quality": 0.75,
  "type": "unknown",
  "hash": "f66168437f38fd54d018cb51c25323c6fbec45d9cc3db4a4288deb0d96ca99fe",
  "language": "en",
  "original_language": "en",
  "timestamp": "2026-02-27T17:42:52.419454",
  "metadata": {}
}