{
  "id": "ae7339335e64ad46",
  "content": "Evolved code for evolve_fd2c1d: def auto_evolve_fd2c1d_1772557390 arg1, arg2 : result None result arg1 arg2 result...",
  "summary": "Evolved code for evolve_fd2c1d: def auto_evolve_fd2c1d_1772557390 arg1, arg2 : result None result arg1 arg2 result...",
  "key_points": [
    "Evolved code for evolve_fd2c1d: def auto_evolve_fd2c1d_1772557390 arg1, arg2 : result None result arg1 arg2 result..."
  ],
  "keywords": [
    "result",
    "arg1",
    "arg2",
    "evolved",
    "code",
    "evolve_fd2c1d",
    "def",
    "auto_evolve_fd2c1d_1772557390",
    "none"
  ],
  "source": "evolution",
  "length": 117,
  "quality": 0.6897435897435897,
  "type": "unknown",
  "hash": "ae7339335e64ad466257a719c408e7ee569fc60f9bd57d9e66c06ea06b2eceef",
  "language": "en",
  "original_language": "en",
  "timestamp": "2026-03-04T01:03:15.382643",
  "metadata": {}
}