{
  "id": "94ee6d1c756560e5",
  "content": "Evolved code for evolve_67fb6e: def auto_evolve_67fb6e_1772343089 arg1, arg2 : result None result arg1 arg2 result...",
  "summary": "Evolved code for evolve_67fb6e: def auto_evolve_67fb6e_1772343089 arg1, arg2 : result None result arg1 arg2 result...",
  "key_points": [
    "Evolved code for evolve_67fb6e: def auto_evolve_67fb6e_1772343089 arg1, arg2 : result None result arg1 arg2 result..."
  ],
  "keywords": [
    "result",
    "arg1",
    "arg2",
    "evolved",
    "code",
    "evolve_67fb6e",
    "def",
    "auto_evolve_67fb6e_1772343089",
    "none"
  ],
  "source": "evolution",
  "length": 117,
  "quality": 0.6829059829059829,
  "type": "unknown",
  "hash": "94ee6d1c756560e58cf08c3c1756089d772c2dff4a84889877c5b7336ecd6a5b",
  "language": "en",
  "original_language": "en",
  "timestamp": "2026-03-01T13:31:36.893639",
  "metadata": {}
}