{
  "id": "310961bd17573eb6",
  "content": "GitHub public-apis public-apis: A collective list of free APIs 403237",
  "summary": "GitHub public-apis public-apis: A collective list of free APIs 403237",
  "key_points": [
    "GitHub public-apis public-apis: A collective list of free APIs 403237"
  ],
  "keywords": [
    "apis",
    "public",
    "github",
    "collective",
    "list",
    "free",
    "403237"
  ],
  "source": "github:trending",
  "length": 69,
  "quality": 0.7956521739130435,
  "type": "unknown",
  "hash": "310961bd17573eb6d521095b510d16acf791e631793c09cfdde449c190f5739d",
  "language": "en",
  "original_language": "en",
  "timestamp": "2026-03-03T21:39:38.468277",
  "metadata": {}
}