{
  "id": "18775d6848f4c3ce",
  "content": "Evolved code for evolve_0a4030: def auto_evolve_0a4030_1772344251 arg1, arg2 : result None result arg1 arg2 result...",
  "summary": "Evolved code for evolve_0a4030: def auto_evolve_0a4030_1772344251 arg1, arg2 : result None result arg1 arg2 result...",
  "key_points": [
    "Evolved code for evolve_0a4030: def auto_evolve_0a4030_1772344251 arg1, arg2 : result None result arg1 arg2 result..."
  ],
  "keywords": [
    "result",
    "arg1",
    "arg2",
    "evolved",
    "code",
    "evolve_0a4030",
    "def",
    "auto_evolve_0a4030_1772344251",
    "none"
  ],
  "source": "evolution",
  "length": 117,
  "quality": 0.4684615384615385,
  "type": "unknown",
  "hash": "18775d6848f4c3cee6cc5ec9e2b7d88ece193278caced84b21dda1aa70c6f828",
  "language": "en",
  "original_language": "en",
  "timestamp": "2026-03-01T13:50:57.679822",
  "metadata": {}
}