{
  "id": "4e72b97058e11f45",
  "content": "GitHub vinta awesome-python: An opinionated list of awesome Python frameworks, libraries, software and resources. 285739",
  "summary": "GitHub vinta awesome-python: An opinionated list of awesome Python frameworks, libraries, software and resources. 285739",
  "key_points": [
    "GitHub vinta awesome-python: An opinionated list of awesome Python frameworks, libraries, software and resources.",
    "285739"
  ],
  "keywords": [
    "awesome",
    "python",
    "github",
    "vinta",
    "opinionated",
    "list",
    "frameworks",
    "libraries",
    "software",
    "resources",
    "285739"
  ],
  "source": "github:trending",
  "length": 120,
  "quality": 0.9166666666666666,
  "type": "unknown",
  "hash": "4e72b97058e11f45b6456b9f4121507ca0882b71c68c35f65e1e705e74ca84b4",
  "language": "en",
  "original_language": "en",
  "timestamp": "2026-03-06T05:39:10.779367",
  "metadata": {}
}