{
  "id": "1d5b91d9e4b0267a",
  "content": "GitHub public-apis public-apis: A collective list of free APIs 401151",
  "summary": "GitHub public-apis public-apis: A collective list of free APIs 401151",
  "key_points": [
    "GitHub public-apis public-apis: A collective list of free APIs 401151"
  ],
  "keywords": [
    "apis",
    "public",
    "github",
    "collective",
    "list",
    "free",
    "401151"
  ],
  "source": "github:trending",
  "length": 69,
  "quality": 0.7956521739130435,
  "type": "unknown",
  "hash": "1d5b91d9e4b0267a950cf53c8136382fd1867dd61a060eb13250dddc99a7e897",
  "language": "en",
  "original_language": "en",
  "timestamp": "2026-02-28T21:42:30.646837",
  "metadata": {}
}