{
  "id": "f46852ac64c13357",
  "content": "Evolved code for evolve_5c0f73: def auto_evolve_5c0f73_1772341576 arg1, arg2 : result None result arg1 arg2 result...",
  "summary": "Evolved code for evolve_5c0f73: def auto_evolve_5c0f73_1772341576 arg1, arg2 : result None result arg1 arg2 result...",
  "key_points": [
    "Evolved code for evolve_5c0f73: def auto_evolve_5c0f73_1772341576 arg1, arg2 : result None result arg1 arg2 result..."
  ],
  "keywords": [
    "result",
    "arg1",
    "arg2",
    "evolved",
    "code",
    "evolve_5c0f73",
    "def",
    "auto_evolve_5c0f73_1772341576",
    "none"
  ],
  "source": "evolution",
  "length": 117,
  "quality": 0.6760683760683761,
  "type": "unknown",
  "hash": "f46852ac64c13357e8fce40ac980dff1341fa80332b7d79a0fa4faba367bedd2",
  "language": "en",
  "original_language": "en",
  "timestamp": "2026-03-01T13:06:23.474504",
  "metadata": {}
}